GStruct-0.1.200209.1.dist-info/DESCRIPTION.rst
GStruct-0.1.200209.1.dist-info/METADATA
GStruct-0.1.200209.1.dist-info/RECORD
GStruct-0.1.200209.1.dist-info/WHEEL
GStruct-0.1.200209.1.dist-info/metadata.json
GStruct-0.1.200209.1.dist-info/top_level.txt
gstruct/__init__.py
gstruct/gsbase.py
gstruct/gsconst.py
gstruct/gsinterface.py
